agora_redis_client/__init__.py
agora_redis_client/redis_client.py
agora_redis_client/version.py
agora_redis_client-3.0.2.dist-info/licenses/LICENSE
agora_redis_client-3.0.2.dist-info/WHEEL
agora_redis_client-3.0.2.dist-info/METADATA
agora_redis_client-3.0.2.dist-info/RECORD
