Metadata-Version: 2.4
Name: agora_redis_client
Version: 3.0.2
Summary: Redis Client for the Agora Edge Apps SDK 2.0 (Python)
Author-email: AgoraIoT <agoraiot@slb.com>
Classifier: License :: OSI Approved :: Apache Software License
License-File: LICENSE
Requires-Dist: agora_logging == 3.0.2
Requires-Dist: agora_config == 3.0.2
Requires-Dist: fakeredis == 2.23.2
Requires-Dist: redis == 7.*
Project-URL: Home, https://slb-edge.github.io
